Khayyam-3.0.17.dist-info/DESCRIPTION.rst
Khayyam-3.0.17.dist-info/METADATA
Khayyam-3.0.17.dist-info/RECORD
Khayyam-3.0.17.dist-info/WHEEL
Khayyam-3.0.17.dist-info/metadata.json
Khayyam-3.0.17.dist-info/top_level.txt
Khayyam-3.0.17.dist-info/zip-safe
khayyam/__init__.py
khayyam/algorithms.py
khayyam/algorithms_c.cpython-36m-darwin.so
khayyam/algorithms_pure.py
khayyam/compat.py
khayyam/constants.py
khayyam/helpers.py
khayyam/jalali_date.py
khayyam/jalali_datetime.py
khayyam/timezones.py
khayyam/formatting/__init__.py
khayyam/formatting/constants.py
khayyam/formatting/formatters.py
khayyam/formatting/directives/__init__.py
khayyam/formatting/directives/ampm.py
khayyam/formatting/directives/base.py
khayyam/formatting/directives/day.py
khayyam/formatting/directives/month.py
khayyam/formatting/directives/persian.py
khayyam/formatting/directives/time.py
khayyam/formatting/directives/tz.py
khayyam/formatting/directives/year.py
khayyam/tests/__init__.py
khayyam/tests/test_algorithms.py
khayyam/tests/test_jalali_date.py
khayyam/tests/test_jalali_date_formatter.py
khayyam/tests/test_jalali_datetime.py
khayyam/tests/test_jalali_datetime_formatter.py
khayyam/tests/test_timezone.py
